{"title":"nike Zoom Fly 5防滑耐磨低帮跑步鞋绿色多少钱","slug":"nike Zoom Fly 5防滑耐磨低帮跑步鞋绿色","date":"2022-12-09T07:03:15.000Z","updated":"2022-12-09T12:39:46.686Z","comments":true,"path":"api/articles/nike Zoom Fly 5防滑耐磨低帮跑步鞋绿色.json","excerpt":null,"covers":["https://xcimg.szwego.com/20221207/i1670399228_3210_0.jpg","https://xcimg.szwego.com/20221207/i1670399228_6896_1.jpg","https://xcimg.szwego.com/20221207/i1670399228_3361_2.jpg","https://xcimg.szwego.com/20221207/i1670399228_3320_3.jpg","https://xcimg.szwego.com/20221207/i1670399228_1390_4.jpg","https://xcimg.szwego.com/20221207/i1670399228_611_5.jpg","https://xcimg.szwego.com/20221207/i1670399228_8339_6.jpg","https://xcimg.szwego.com/20221207/i1670399228_4251_7.jpg","https://xcimg.szwego.com/20221207/i1670399228_6054_8.jpg","https://xcimg.szwego.com/20221207/i1670399263_3710_0.jpg","https://xcimg.szwego.com/20221207/i1670399263_7414_1.jpg","https://xcimg.szwego.com/20221207/i1670399263_6463_2.jpg","https://xcimg.szwego.com/20221207/i1670399263_8704_3.jpg","https://xcimg.szwego.com/20221207/i1670399263_9715_4.jpg","https://xcimg.szwego.com/20221207/i1670399263_5285_5.jpg","https://xcimg.szwego.com/20221207/i1670399263_3782_6.jpg","https://xcimg.szwego.com/20221207/i1670399263_8191_7.jpg","https://xcimg.szwego.com/20221207/i1670399263_9165_8.jpg"],"content":"<video src='https://xcimg.szwego.com/20221207/o1670399188_8197_1.mp4' type='video/mp4' controls='controls'  width='100%' height='100%'>\n</video>\n\n<p>nike Zoom Fly 5防滑耐磨低帮跑步鞋绿色多少钱？耐克Zoom Fly 5防滑耐磨低帮跑步鞋绿色，主货号DZ4783-304，发售价格￥999（仅供参考），当前市场价779元。</p>\n<p>单只重量266.5g；全掌科技：碳板，SR-02泡棉，ZoomX泡棉；鞋面科技：Flyknit；鞋底功能：缓震回弹稳定；鞋面功能：透气包裹；适合场地：竞速跑/马拉松长跑</p>\n<p>双层鞋面，上层梭织鞋面，内层贾卡鞋面，透气一般。尺码标准但是鞋楦整体偏大，整体包裹都不是特别极致，就足弓处因为鞋舌很厚才感觉包裹有所加强。</p>\n<p>后跟海绵填充不多但是鞋带孔的位置靠前因此鞋口非常大，感觉很松，必须拉紧最后一个鞋带孔，貌似zoomfly系列包裹性都是诟病的地方。</p>\n<p>整个鞋面貌似质感不错，后跟也加入一块硬质港宝稳固力线。中底和鞋垫都是用的回收的zoomx:边角材料做成。软弹依旧，但是形变量会有所降低，加上胶水的原因重量会有所上升。</p>\n<p>Zoom Fly5内部还放置了一块碳板，不是铲型的，而是一块平面板，放置的角度也偏平，放置位置也偏高，但助推一样强劲。适用于日常节奏训练和比赛，EKIDEN驿传配色更抓眼球。</p>\n<p><img src=\"https://xcimg.szwego.com/20221207/i1670399228_3210_0.jpg\" alt=\"nike Zoom Fly 5防滑耐磨低帮跑步鞋绿色多少钱\"></p>\n<p><img src=\"https://xcimg.szwego.com/20221207/i1670399228_6896_1.jpg\" alt=\"nike Zoom Fly 5防滑耐磨低帮跑步鞋绿色多少钱\"></p>\n<p><img src=\"https://xcimg.szwego.com/20221207/i1670399228_3361_2.jpg\" alt=\"nike Zoom Fly 5防滑耐磨低帮跑步鞋绿色多少钱\"></p>\n<p><img src=\"https://xcimg.szwego.com/20221207/i1670399228_3320_3.jpg\" alt=\"nike Zoom Fly 5防滑耐磨低帮跑步鞋绿色多少钱\"></p>\n<p><img src=\"https://xcimg.szwego.com/20221207/i1670399228_1390_4.jpg\" alt=\"nike Zoom Fly 5防滑耐磨低帮跑步鞋绿色多少钱\"></p>\n<p><img src=\"https://xcimg.szwego.com/20221207/i1670399228_611_5.jpg\" alt=\"nike Zoom Fly 5防滑耐磨低帮跑步鞋绿色多少钱\"></p>\n<p><img src=\"https://xcimg.szwego.com/20221207/i1670399228_8339_6.jpg\" alt=\"nike Zoom Fly 5防滑耐磨低帮跑步鞋绿色多少钱\"></p>\n<p><img src=\"https://xcimg.szwego.com/20221207/i1670399228_4251_7.jpg\" alt=\"nike Zoom Fly 5防滑耐磨低帮跑步鞋绿色多少钱\"></p>\n<p><img src=\"https://xcimg.szwego.com/20221207/i1670399228_6054_8.jpg\" alt=\"nike Zoom Fly 5防滑耐磨低帮跑步鞋绿色多少钱\"></p>\n<p><img src=\"https://xcimg.szwego.com/20221207/i1670399263_3710_0.jpg\" alt=\"nike Zoom Fly 5防滑耐磨低帮跑步鞋绿色多少钱\"></p>\n<p><img src=\"https://xcimg.szwego.com/20221207/i1670399263_7414_1.jpg\" alt=\"nike Zoom Fly 5防滑耐磨低帮跑步鞋绿色多少钱\"></p>\n<p><img src=\"https://xcimg.szwego.com/20221207/i1670399263_6463_2.jpg\" alt=\"nike Zoom Fly 5防滑耐磨低帮跑步鞋绿色多少钱\"></p>\n<p><img src=\"https://xcimg.szwego.com/20221207/i1670399263_8704_3.jpg\" alt=\"nike Zoom Fly 5防滑耐磨低帮跑步鞋绿色多少钱\"></p>\n<p><img src=\"https://xcimg.szwego.com/20221207/i1670399263_9715_4.jpg\" alt=\"nike Zoom Fly 5防滑耐磨低帮跑步鞋绿色多少钱\"></p>\n<p><img src=\"https://xcimg.szwego.com/20221207/i1670399263_5285_5.jpg\" alt=\"nike Zoom Fly 5防滑耐磨低帮跑步鞋绿色多少钱\"></p>\n<p><img src=\"https://xcimg.szwego.com/20221207/i1670399263_3782_6.jpg\" alt=\"nike Zoom Fly 5防滑耐磨低帮跑步鞋绿色多少钱\"></p>\n<p><img src=\"https://xcimg.szwego.com/20221207/i1670399263_8191_7.jpg\" alt=\"nike Zoom Fly 5防滑耐磨低帮跑步鞋绿色多少钱\"></p>\n<p><img src=\"https://xcimg.szwego.com/20221207/i1670399263_9165_8.jpg\" alt=\"nike Zoom Fly 5防滑耐磨低帮跑步鞋绿色多少钱\"></p>\n","more":"<video src='https://xcimg.szwego.com/20221207/o1670399188_8197_1.mp4' type='video/mp4' controls='controls'  width='100%' height='100%'>\n</video>\n\n<p>nike Zoom Fly 5防滑耐磨低帮跑步鞋绿色多少钱？耐克Zoom Fly 5防滑耐磨低帮跑步鞋绿色，主货号DZ4783-304，发售价格￥999（仅供参考），当前市场价779元。</p>\n<p>单只重量266.5g；全掌科技：碳板，SR-02泡棉，ZoomX泡棉；鞋面科技：Flyknit；鞋底功能：缓震回弹稳定；鞋面功能：透气包裹；适合场地：竞速跑/马拉松长跑</p>\n<p>双层鞋面，上层梭织鞋面，内层贾卡鞋面，透气一般。尺码标准但是鞋楦整体偏大，整体包裹都不是特别极致，就足弓处因为鞋舌很厚才感觉包裹有所加强。</p>\n<p>后跟海绵填充不多但是鞋带孔的位置靠前因此鞋口非常大，感觉很松，必须拉紧最后一个鞋带孔，貌似zoomfly系列包裹性都是诟病的地方。</p>\n<p>整个鞋面貌似质感不错，后跟也加入一块硬质港宝稳固力线。中底和鞋垫都是用的回收的zoomx:边角材料做成。软弹依旧，但是形变量会有所降低，加上胶水的原因重量会有所上升。</p>\n<p>Zoom Fly5内部还放置了一块碳板，不是铲型的，而是一块平面板，放置的角度也偏平，放置位置也偏高，但助推一样强劲。适用于日常节奏训练和比赛，EKIDEN驿传配色更抓眼球。</p>\n<p><img src=\"https://xcimg.szwego.com/20221207/i1670399228_3210_0.jpg\" alt=\"nike Zoom Fly 5防滑耐磨低帮跑步鞋绿色多少钱\"></p>\n<p><img src=\"https://xcimg.szwego.com/20221207/i1670399228_6896_1.jpg\" alt=\"nike Zoom Fly 5防滑耐磨低帮跑步鞋绿色多少钱\"></p>\n<p><img src=\"https://xcimg.szwego.com/20221207/i1670399228_3361_2.jpg\" alt=\"nike Zoom Fly 5防滑耐磨低帮跑步鞋绿色多少钱\"></p>\n<p><img src=\"https://xcimg.szwego.com/20221207/i1670399228_3320_3.jpg\" alt=\"nike Zoom Fly 5防滑耐磨低帮跑步鞋绿色多少钱\"></p>\n<p><img src=\"https://xcimg.szwego.com/20221207/i1670399228_1390_4.jpg\" alt=\"nike Zoom Fly 5防滑耐磨低帮跑步鞋绿色多少钱\"></p>\n<p><img src=\"https://xcimg.szwego.com/20221207/i1670399228_611_5.jpg\" alt=\"nike Zoom Fly 5防滑耐磨低帮跑步鞋绿色多少钱\"></p>\n<p><img src=\"https://xcimg.szwego.com/20221207/i1670399228_8339_6.jpg\" alt=\"nike Zoom Fly 5防滑耐磨低帮跑步鞋绿色多少钱\"></p>\n<p><img src=\"https://xcimg.szwego.com/20221207/i1670399228_4251_7.jpg\" alt=\"nike Zoom Fly 5防滑耐磨低帮跑步鞋绿色多少钱\"></p>\n<p><img src=\"https://xcimg.szwego.com/20221207/i1670399228_6054_8.jpg\" alt=\"nike Zoom Fly 5防滑耐磨低帮跑步鞋绿色多少钱\"></p>\n<p><img src=\"https://xcimg.szwego.com/20221207/i1670399263_3710_0.jpg\" alt=\"nike Zoom Fly 5防滑耐磨低帮跑步鞋绿色多少钱\"></p>\n<p><img src=\"https://xcimg.szwego.com/20221207/i1670399263_7414_1.jpg\" alt=\"nike Zoom Fly 5防滑耐磨低帮跑步鞋绿色多少钱\"></p>\n<p><img src=\"https://xcimg.szwego.com/20221207/i1670399263_6463_2.jpg\" alt=\"nike Zoom Fly 5防滑耐磨低帮跑步鞋绿色多少钱\"></p>\n<p><img src=\"https://xcimg.szwego.com/20221207/i1670399263_8704_3.jpg\" alt=\"nike Zoom Fly 5防滑耐磨低帮跑步鞋绿色多少钱\"></p>\n<p><img src=\"https://xcimg.szwego.com/20221207/i1670399263_9715_4.jpg\" alt=\"nike Zoom Fly 5防滑耐磨低帮跑步鞋绿色多少钱\"></p>\n<p><img src=\"https://xcimg.szwego.com/20221207/i1670399263_5285_5.jpg\" alt=\"nike Zoom Fly 5防滑耐磨低帮跑步鞋绿色多少钱\"></p>\n<p><img src=\"https://xcimg.szwego.com/20221207/i1670399263_3782_6.jpg\" alt=\"nike Zoom Fly 5防滑耐磨低帮跑步鞋绿色多少钱\"></p>\n<p><img src=\"https://xcimg.szwego.com/20221207/i1670399263_8191_7.jpg\" alt=\"nike Zoom Fly 5防滑耐磨低帮跑步鞋绿色多少钱\"></p>\n<p><img src=\"https://xcimg.szwego.com/20221207/i1670399263_9165_8.jpg\" alt=\"nike Zoom Fly 5防滑耐磨低帮跑步鞋绿色多少钱\"></p>\n","categories":[{"name":"潮鞋穿搭","path":"api/categories/潮鞋穿搭.json"}],"tags":[]}