{"title":"椰子350鞋码偏大还是偏小","slug":"椰子350鞋码偏大还是偏小","date":"2022-04-14T09:03:35.000Z","updated":"2022-11-07T02:50:12.099Z","comments":true,"path":"api/articles/椰子350鞋码偏大还是偏小.json","excerpt":null,"covers":["https://img.8dsport.com/image/Snipaste_2022-03-26_18-37-31.png","https://img.8dsport.com/image/Snipaste_2022-03-26_18-37-03.png","https://img.8dsport.com/image/Snipaste_2022-03-24_14-47-32.png"],"content":"<p>椰子350鞋码偏大还是偏小？椰子350鞋码是偏小的。</p>\n<p>包括椰子350 500 700，一般都可以在自己平时尺码上选择大一码即可</p>\n<p><img src=\"https://img.8dsport.com/image/Snipaste_2022-03-26_18-37-31.png\" alt=\"椰子350鞋码偏大还是偏小\"></p>\n<p>当然也可以看看自己脚长，和椰子标准尺码进行对比，一般来说大一码没啥问题</p>\n<p><img src=\"https://img.8dsport.com/image/Snipaste_2022-03-26_18-37-03.png\" alt=\"椰子350鞋码偏大还是偏小\"></p>\n<p>不同版本的椰子350鞋码也是不一样的</p>\n<p>初代椰子350鞋码都偏小，建议加大1~1.5码</p>\n<p>2016以前的老灰橙、黄油、黑红字、白斑马、黄斑马等，鞋头都比较挤脚，脚宽的或大拇指较大的，建议加大1.5~2码</p>\n<p>2016之后的，基本只要加大1码就好了，因为鞋头不会再那么偏了</p>\n<p><img src=\"https://img.8dsport.com/image/Snipaste_2022-03-24_14-47-32.png\" alt=\"椰子350鞋码偏大还是偏小\"></p>\n","more":"<p>椰子350鞋码偏大还是偏小？椰子350鞋码是偏小的。</p>\n<p>包括椰子350 500 700，一般都可以在自己平时尺码上选择大一码即可</p>\n<p><img src=\"https://img.8dsport.com/image/Snipaste_2022-03-26_18-37-31.png\" alt=\"椰子350鞋码偏大还是偏小\"></p>\n<p>当然也可以看看自己脚长，和椰子标准尺码进行对比，一般来说大一码没啥问题</p>\n<p><img src=\"https://img.8dsport.com/image/Snipaste_2022-03-26_18-37-03.png\" alt=\"椰子350鞋码偏大还是偏小\"></p>\n<p>不同版本的椰子350鞋码也是不一样的</p>\n<p>初代椰子350鞋码都偏小，建议加大1~1.5码</p>\n<p>2016以前的老灰橙、黄油、黑红字、白斑马、黄斑马等，鞋头都比较挤脚，脚宽的或大拇指较大的，建议加大1.5~2码</p>\n<p>2016之后的，基本只要加大1码就好了，因为鞋头不会再那么偏了</p>\n<p><img src=\"https://img.8dsport.com/image/Snipaste_2022-03-24_14-47-32.png\" alt=\"椰子350鞋码偏大还是偏小\"></p>\n","categories":[{"name":"椰子350","path":"api/categories/椰子350.json"}],"tags":[]}